lsq/__init__.py
lsq/__main__.py
lsq/apihelper.py
lsq/config.py
lsq/exceptions.py
lsq/leadapi.py
lsq/main.py
lsq/package_data.dat
lsq/parser.py
lsq-0.0.15.dist-info/LICENSE
lsq-0.0.15.dist-info/METADATA
lsq-0.0.15.dist-info/WHEEL
lsq-0.0.15.dist-info/top_level.txt
lsq-0.0.15.dist-info/RECORD
