Metadata-Version: 2.1
Name: lsq
Version: 0.0.15
Summary: Added Help options in __main__
Home-page: https://github.com/seanjin17/lsq-python
Author: Anand Sandilya
Author-email: anand.sandilya@leadsquared.com
License: UNKNOWN
Keywords: leadsquared lsq lsqpython lsqpip
Platform: UNKNOWN
Classifier: Intended Audience :: Developers
Classifier: Programming Language :: Python :: 3
Classifier: License :: OSI Approved :: MIT License
Classifier: Operating System :: OS Independent
Requires-Dist: requests
